phenigraph/__init__.py
phenigraph/gui.py
phenigraph/objet.py
phenigraph-0.2.0.3.dist-info/LICENSE
phenigraph-0.2.0.3.dist-info/METADATA
phenigraph-0.2.0.3.dist-info/WHEEL
phenigraph-0.2.0.3.dist-info/top_level.txt
phenigraph-0.2.0.3.dist-info/RECORD
