Metadata-Version: 2.1
Name: phenigraph
Version: 0.2.0.3
Summary: A library to plot, store and replot matplotlib plot easly and reproducibly
Home-page: https://github.com/HuetPaul/PheniGraph
Author: Paul Huet
License: UNKNOWN
Platform: UNKNOWN
Requires-Dist: PyQt5
Requires-Dist: matplotlib
Requires-Dist: numpy
Requires-Dist: scipy
